latestTouki/__init__.py
latestTouki/morita_toukiDateList_to_Latestyyyymmdd.py
latestTouki-1.2.0.dist-info/LICENSE
latestTouki-1.2.0.dist-info/METADATA
latestTouki-1.2.0.dist-info/WHEEL
latestTouki-1.2.0.dist-info/top_level.txt
latestTouki-1.2.0.dist-info/RECORD
